{
  "catalogs": [
    {
      "name": "tcph",
      "databases": [
        {
          "name": "tpc-h",
          "tables": [
            {
              "name": "customer",
              "description": "Customer information from the TPC-H benchmark.",
              "partitions": [],
              "columns": [
                {
                  "name": "c_custkey",
                  "type": "Int64"
                },
                {
                  "name": "c_name",
                  "type": "String"
                },
                {
                  "name": "c_address",
                  "type": "String"
                },
                {
                  "name": "c_nationkey",
                  "type": "Int64"
                },
                {
                  "name": "c_phone",
                  "type": "String"
                },
                {
                  "name": "c_acctbal",
                  "type": "Float64"
                },
                {
                  "name": "c_mktsegment",
                  "type": "String"
                },
                {
                  "name": "c_comment",
                  "type": "String"
                }
              ],
              "selected_columns": null,
              "supports_sql_filter": false,
              "table_type": "FUNCTION",
              "latency_info": "Updated daily by the customer_profile_sync DAG on Airflow",
              "example_notebook": null,
              "data_input": "Customer profile data from CRM system <code>/api/customers/profiles</code> endpoint"
            },
            {
              "name": "lineitem",
              "description": "Line item information from the TPC-H benchmark.",
              "partitions": [],
              "columns": [
                {
                  "name": "l_orderkey",
                  "type": "Int64"
                },
                {
                  "name": "l_partkey",
                  "type": "Int64"
                },
                {
                  "name": "l_suppkey",
                  "type": "Int64"
                },
                {
                  "name": "l_linenumber",
                  "type": "Int64"
                },
                {
                  "name": "l_quantity",
                  "type": "Float64"
                },
                {
                  "name": "l_extendedprice",
                  "type": "Float64"
                },
                {
                  "name": "l_discount",
                  "type": "Float64"
                },
                {
                  "name": "l_tax",
                  "type": "Float64"
                },
                {
                  "name": "l_returnflag",
                  "type": "String"
                },
                {
                  "name": "l_linestatus",
                  "type": "String"
                },
                {
                  "name": "l_shipdate",
                  "type": "String"
                },
                {
                  "name": "l_commitdate",
                  "type": "String"
                },
                {
                  "name": "l_receiptdate",
                  "type": "String"
                },
                {
                  "name": "l_shipinstruct",
                  "type": "String"
                },
                {
                  "name": "l_shipmode",
                  "type": "String"
                },
                {
                  "name": "l_comment",
                  "type": "String"
                }
              ],
              "selected_columns": null,
              "supports_sql_filter": false,
              "table_type": "FUNCTION",
              "latency_info": "Updated hourly by the order_line_sync DAG on Airflow",
              "example_notebook": null,
              "data_input": "Order line items from fulfillment system <code>/api/orders/line_items</code> endpoint"
            },
            {
              "name": "nation",
              "description": "\n    Nation information from the TPC-H benchmark.\n    Contains details about nations including name and region.\n    ",
              "partitions": [
                {
                  "column_name": "n_nationkey",
                  "type_annotation": "int",
                  "value": 1
                }
              ],
              "columns": [
                {
                  "name": "n_nationkey",
                  "type": "int64"
                },
                {
                  "name": "n_name",
                  "type": "string"
                },
                {
                  "name": "n_regionkey",
                  "type": "int64"
                },
                {
                  "name": "n_comment",
                  "type": "string"
                }
              ],
              "selected_columns": null,
              "supports_sql_filter": false,
              "table_type": "PARQUET",
              "latency_info": "Static reference data, updated quarterly",
              "example_notebook": "https://example.com/notebooks/geographic_analysis.ipynb",
              "data_input": "Geographic reference data from global operations database"
            },
            {
              "name": "orders",
              "description": "\n    Order information from the TPC-H benchmark.\n    Contains order details including status, total price, and order date.\n    ",
              "partitions": [
                {
                  "column_name": "o_orderkey",
                  "type_annotation": "int",
                  "value": 1
                }
              ],
              "columns": [
                {
                  "name": "o_orderkey",
                  "type": "int64"
                },
                {
                  "name": "o_custkey",
                  "type": "int64"
                },
                {
                  "name": "o_orderstatus",
                  "type": "string"
                },
                {
                  "name": "o_totalprice",
                  "type": "decimal128(12, 2)"
                },
                {
                  "name": "o_orderdate",
                  "type": "date32[day]"
                },
                {
                  "name": "o_orderpriority",
                  "type": "string"
                },
                {
                  "name": "o_clerk",
                  "type": "string"
                },
                {
                  "name": "o_shippriority",
                  "type": "int32"
                },
                {
                  "name": "o_comment",
                  "type": "string"
                }
              ],
              "selected_columns": null,
              "supports_sql_filter": true,
              "table_type": "DELTA_LAKE",
              "latency_info": "Near real-time order processing with 5-minute delay",
              "example_notebook": "https://example.com/notebooks/order_analysis.ipynb",
              "data_input": "Order data from e-commerce and retail systems"
            },
            {
              "name": "part",
              "description": "\n    Part information from the TPC-H benchmark.\n    Contains details about parts including name, manufacturer, brand, and retail price.\n    ",
              "partitions": [
                {
                  "column_name": "p_partkey",
                  "type_annotation": "int",
                  "value": 1
                }
              ],
              "columns": [
                {
                  "name": "p_partkey",
                  "type": "int64"
                },
                {
                  "name": "p_name",
                  "type": "string"
                },
                {
                  "name": "p_mfgr",
                  "type": "string"
                },
                {
                  "name": "p_brand",
                  "type": "string"
                },
                {
                  "name": "p_type",
                  "type": "string"
                },
                {
                  "name": "p_size",
                  "type": "int32"
                },
                {
                  "name": "p_container",
                  "type": "string"
                },
                {
                  "name": "p_retailprice",
                  "type": "decimal128(12, 2)"
                },
                {
                  "name": "p_comment",
                  "type": "string"
                }
              ],
              "selected_columns": null,
              "supports_sql_filter": true,
              "table_type": "DELTA_LAKE",
              "latency_info": "Daily batch updates from manufacturing ERP system",
              "example_notebook": "https://example.com/notebooks/part_analysis.ipynb",
              "data_input": "Part catalog data from manufacturing systems, updated daily"
            },
            {
              "name": "partsupp",
              "description": "\n    Part supplier information from the TPC-H benchmark.\n    Contains details about parts supplied by suppliers including available quantity and supply cost.\n    ",
              "partitions": [
                {
                  "column_name": "ps_partkey",
                  "type_annotation": "int",
                  "value": 1
                },
                {
                  "column_name": "ps_suppkey",
                  "type_annotation": "int",
                  "value": 1
                }
              ],
              "columns": [
                {
                  "name": "ps_partkey",
                  "type": "int64"
                },
                {
                  "name": "ps_suppkey",
                  "type": "int64"
                },
                {
                  "name": "ps_availqty",
                  "type": "int32"
                },
                {
                  "name": "ps_supplycost",
                  "type": "decimal128(12, 2)"
                },
                {
                  "name": "ps_comment",
                  "type": "string"
                }
              ],
              "selected_columns": null,
              "supports_sql_filter": false,
              "table_type": "PARQUET",
              "latency_info": "Real-time updates from supplier inventory management systems",
              "example_notebook": "https://example.com/notebooks/supplier_analysis.ipynb",
              "data_input": "Supplier inventory and pricing data from procurement systems"
            },
            {
              "name": "region",
              "description": "Region information from the TPC-H benchmark.",
              "partitions": [],
              "columns": [
                {
                  "name": "r_regionkey",
                  "type": "Int64"
                },
                {
                  "name": "r_name",
                  "type": "String"
                },
                {
                  "name": "r_comment",
                  "type": "String"
                }
              ],
              "selected_columns": null,
              "supports_sql_filter": false,
              "table_type": "FUNCTION",
              "latency_info": "Updated monthly by the region_hierarchy_sync DAG on Airflow",
              "example_notebook": null,
              "data_input": "Regional hierarchy data from global operations <code>/api/regions/hierarchy</code> endpoint"
            },
            {
              "name": "supplier",
              "description": "Supplier information from the TPC-H benchmark.",
              "partitions": [],
              "columns": [
                {
                  "name": "s_suppkey",
                  "type": "Int64"
                },
                {
                  "name": "s_name",
                  "type": "String"
                },
                {
                  "name": "s_address",
                  "type": "String"
                },
                {
                  "name": "s_nationkey",
                  "type": "Int64"
                },
                {
                  "name": "s_phone",
                  "type": "String"
                },
                {
                  "name": "s_acctbal",
                  "type": "Float64"
                },
                {
                  "name": "s_comment",
                  "type": "String"
                }
              ],
              "selected_columns": null,
              "supports_sql_filter": false,
              "table_type": "FUNCTION",
              "latency_info": "Updated weekly by the supplier_master_sync DAG on Airflow",
              "example_notebook": null,
              "data_input": "Supplier master data from vendor management system <code>/api/suppliers/master</code> endpoint"
            }
          ]
        }
      ]
    }
  ]
}